LICENCE
README.md
setup.py
icpyedu/__init__.py
icpyedu/signer.py
icpyedu.egg-info/PKG-INFO
icpyedu.egg-info/SOURCES.txt
icpyedu.egg-info/dependency_links.txt
icpyedu.egg-info/requires.txt
icpyedu.egg-info/top_level.txt